animrec/animrec.py
animrec/processed_anime.csv
animrec-1.6.dist-info/METADATA
animrec-1.6.dist-info/WHEEL
animrec-1.6.dist-info/entry_points.txt
animrec-1.6.dist-info/top_level.txt
animrec-1.6.dist-info/RECORD
