Metadata-Version: 2.1
Name: animrec
Version: 1.6
Summary: Anime Recommendation System is a project designed to give users Anime Watching recommendations based on the Anime they have already watched using various Machine Learning Techniques
Author-email: Shamsheer <shamsheerkhalid99@gmail.com>
Project-URL: Homepage, https://github.com/5ham5h33r/Anime_Recommendation_System
Project-URL: Bug Tracker, https://github.com/5ham5h33r/Anime_Recommendation_System/issues
Classifier: Programming Language :: Python :: 3
Classifier: License :: OSI Approved :: MIT License
Classifier: Operating System :: OS Independent
Requires-Python: >=3.7
Requires-Dist: scikit-learn
Requires-Dist: numpy
Requires-Dist: pandas
Requires-Dist: regex
